SpearheadClient/__init__.py
SpearheadClient/async_base_client.py
SpearheadClient/base_model.py
SpearheadClient/client.py
SpearheadClient/enums.py
SpearheadClient/exceptions.py
SpearheadClient/fragments.py
SpearheadClient/get_tickets_flat.py
SpearheadClient/get_tickets_full.py
SpearheadClient/input_types.py
SpearheadClient/user_from_token.py
SpearheadClient/work_site_detail.py
SpearheadClient/work_site_ownership.py
SpearheadClient/work_site_search.py
SpearheadClient/work_site_ticket_activity.py
SpearheadClient/AuthInfinity/AuthInfinityHttpClient.py
SpearheadClient/AuthInfinity/requirements.txt
spearheadclient-1.0.3.dist-info/METADATA
spearheadclient-1.0.3.dist-info/WHEEL
spearheadclient-1.0.3.dist-info/licenses/LICENSE
spearheadclient-1.0.3.dist-info/RECORD
