Metadata-Version: 2.4
Name: SpearheadClient
Version: 1.0.3
Summary: A client for the SpearheadOps GraphQL API
Project-URL: Homepage, https://pypi.org/project/SpearheadClient/
Project-URL: Issues, https://pypi.org/project/SpearheadClient/
Author-email: Spearhead Ops <support@spearheadops.com>
License-Expression: MIT
License-File: LICENSE
Classifier: Operating System :: OS Independent
Classifier: Programming Language :: Python :: 3
Requires-Python: >=3.9
Requires-Dist: asyncio
Requires-Dist: httpx
Requires-Dist: pydantic
